MANIFEST.in
README.md
setup.py
sequence2hash/__init__.py
sequence2hash.egg-info/PKG-INFO
sequence2hash.egg-info/SOURCES.txt
sequence2hash.egg-info/dependency_links.txt
sequence2hash.egg-info/top_level.txt