Metadata-Version: 2.1
Name: sequence2hash
Version: 1.1.2
Summary: This tool converts a valid value in a sequence to a hash and contains a path to a valid value in the key field
Home-page: https://github.com/Cuile/sequence2hash
Author: cuile
Author-email: i@cuile.com
License: UNKNOWN
Keywords: tuple dict list sequence hash key/value
Platform: UNKNOWN
